Workbook

Sheet Dados
A1: EMPRESA | B1: EMPRESA (SAP) | C1: CÓDIGO CARGO | D1: CARGO | E1: GRADE | F1: SITUAÇÃO | G1: GRUPO | H1: FAMÍLIA GBS | I1: SUB FAMÍLIA | J1: GRUPO HIERARQUICO | K1: NÍVEL | L1: CBO | M1: REGRA CONTROLE JORNADA | N1: CONTROLE JORNADA | O1: COTA APRENDIZ | P1: TIPO CONTRATO | Q1: SINDICATO | R1: MERCADO SELECIONADO | S1: DESCRIÇÃO SUMÁRIA | T1: Cod. Mercer 2025 | U1: Cod. Mercer 2026
A2: HOLDING | B2: HOLDING | C2: 6110395 | D2: GERENTE ADMINISTRACAO PATRIMONIAL | E2: 11 | F2: ATIVO | G2: Corporativo | H2: Administração & Serviços | I2: Facilities e Serviços Gerais | J2: GA | K2: GA | L2: 142705 | M2: Avaliação de tempos teórica | N2: Não elegível | O2: NAO ELEGIVEL COTA APRENDIZ | P2: CLT | Q2: Preponderante | R2: Elementares | S2: Gerenciar os processos administrativos e tecnicos da area, para que sejam conduzidos, bem como zelar para que estejam em consonancia com os objetivos tracados, alinhando acoes a serem adotadas para o melhor desempenho das responsabilidades da area. | T2: IE.26.002.M30 | U2: IE.26.002.M30
A3: HOLDING | B3: HOLDING | C3: 6109192 | D3: SUPERVISOR ADMINISTRACAO PATRIMONIAL | E3: 9 | F3: ATIVO | G3: Corporativo | H3: Administração & Serviços | I3: Facilities e Serviços Gerais | J3: Supervisor | K3: Supervisor Matriz | L3: 410220 | M3: Avaliação de tempos real | N3: Elegível | O3: NAO ELEGIVEL COTA APRENDIZ | P3: CLT | Q3: Preponderante | R3: Elementares | S3: Conduzir os processos administrativos e tecnicos da area, para que sejam conduzidos com organizacao, bem como zelar para que estejam em consonancia com os objetivos tracados, alinhando acoes a serem adotadas para o melhor desempenho das responsabilidades da area. | T3: IE.26.002.M10 | U3: IE.26.002.M10
A4: HOLDING | B4: HOLDING | C4: 6109193 | D4: ANALISTA ADMINISTRACAO PATRIMONIAL SR | E4: 8 | F4: ATIVO | G4: Corporativo | H4: Administração & Serviços | I4: Facilities e Serviços Gerais | J4: Analista | K4: Analista Sr | L4: 142330 | M4: Avaliação de tempos real | N4: Elegível | O4: NAO ELEGIVEL COTA APRENDIZ | P4: CLT | Q4: Preponderante | R4: Elementares | S4: Garantir que os processos administrativos da area sejam conduzidos com organizacao, a fim de zelar que estejam em consonancia com os objetivos da area e que possam atender as necessidades dos processos conduzidos pela equipe de profissionais tecnicos. | T4: IE.26.002.P30 | U4: IE.26.002.P30
A5: HOLDING | B5: HOLDING | C5: 6109194 | D5: ANALISTA ADMINISTRACAO PATRIMONIAL PL | E5: 6 | F5: ATIVO | G5: Corporativo | H5: Administração & Serviços | I5: Facilities e Serviços Gerais | J5: Analista | K5: Analista Pl | L5: 142330 | M5: Avaliação de tempos real | N5: Elegível | O5: NAO ELEGIVEL COTA APRENDIZ | P5: CLT | Q5: Preponderante | R5: Elementares | S5: Garantir que os processos administrativos da area sejam conduzidos com organizacao, a fim de zelar que estejam em consonancia com os objetivos da area e que possam atender as necessidades dos processos conduzidos pela equipe de profissionais tecnicos. | T5: IE.26.002.P20 | U5: IE.26.002.P20
A6: HOLDING | B6: HOLDING | C6: 6109195 | D6: ANALISTA ADMINISTRACAO PATRIMONIAL JR | E6: 5 | F6: ATIVO | G6: Corporativo | H6: Administração & Serviços | I6: Facilities e Serviços Gerais | J6: Analista | K6: Analista Jr | L6: 142330 | M6: Avaliação de tempos real | N6: Elegível | O6: NAO ELEGIVEL COTA APRENDIZ | P6: CLT | Q6: Preponderante | R6: Elementares | S6: Garantir que os processos administrativos da area sejam conduzidos com organizacao, a fim de zelar que estejam em consonancia com os objetivos da area e que possam atender as necessidades dos processos conduzidos pela equipe de profissionais tecnicos. | T6: IE.26.002.P10 | U6: IE.26.002.P10
A7: HOLDING | B7: HOLDING | C7: 6110394 | D7: ANALISTA ASSISTENTE ADM PATRIMONIAL | E7: 4 | F7: ATIVO | G7: Corporativo | H7: Administração & Serviços | I7: Facilities e Serviços Gerais | J7: Assistente | K7: Assistente | L7: 142330 | M7: Avaliação de tempos real | N7: Elegível | O7: NAO ELEGIVEL COTA APRENDIZ | P7: CLT | Q7: Preponderante | R7: Elementares | S7: Garantir que os processos administrativos da area sejam conduzidos com organizacao, a fim de zelar que estejam em consonancia com os objetivos da area e que possam atender as necessidades dos processos conduzidos pela equipe de profissionais tecnicos. | T7: IE.26.002.S20 | U7: IE.26.002.S20
A8: HOLDING | B8: HOLDING | C8: 6110337 | D8: GERENTE DEPARTAMENTO SECRETARIA GERAL | E8: 13 | F8: INATIVO | G8: Corporativo | H8: Administração & Serviços | I8: Secretaria | J8: GS | K8: GS | L8: 142105 | M8: Avaliação de tempos teórica | N8: Não elegível | O8: NAO ELEGIVEL COTA APRENDIZ | P8: CLT | Q8: Preponderante | R8: Elementares | S8: Liderar as areas sob sua responsabilidade, definindo estrategias de atuacao, missao, visao e objetivos para disseminacao junto ao quadro de colaboradores, de modo a assegurar a concretizacao e maximizacao dos resultados, por meio do relacionamento entre o Banco e clientes internos/externos, garantindo a correta conducao dos negocios, operacoes e processos do departamento, com objetivo de promover o crescimento continuo da Organizacao em consonancia as normas vigentes das entidades regulamentadoras. | T8: IE.26.005.M30 | U8: IE.26.005.M30
A9: HOLDING | B9: HOLDING | C9: 6110338 | D9: GERENTE SUPORTE EXECUTIVO | E9: 11 | F9: ATIVO | G9: Corporativo | H9: Administração & Serviços | I9: Secretaria | J9: GA | K9: GA | L9: 142105 | M9: Avaliação de tempos teórica | N9: Não elegível | O9: NAO ELEGIVEL COTA APRENDIZ | P9: CLT | Q9: Preponderante | R9: Elementares | S9: Gerenciar o apoio pela equipe a Diretoria Executiva no que tange a atividades de secretaria,como, agendamento de compromissos, atendimentos telefonico e afins. | T9: IE.26.005.M20 | U9: IE.26.005.M20
A10: HOLDING | B10: HOLDING | C10: 6110562 | D10: COORDENADOR SUPORTE EXECUTIVO | E10: 10 | F10: ATIVO | G10: Corporativo | H10: Administração & Serviços | I10: Secretaria | J10: Coordenador | K10: Coordenador Matriz | L10: 142105 | M10: Avaliação de tempos real | N10: Elegível | O10: NAO ELEGIVEL COTA APRENDIZ | P10: CLT | Q10: Preponderante | R10: Elementares | S10: Coordenar o apoio pela equipe a Diretoria Executiva no que tange a atividades de secretaria,como, agendamento de compromissos, atendimentos telefonico e afins. | T10: IE.26.005.P41 | U10: IE.26.005.P41
A11: HOLDING | B11: HOLDING | C11: 6111274 | D11: SUPERVISOR SUPORTE EXECUTIVO | E11: 9 | F11: ATIVO | G11: Corporativo | H11: Administração & Serviços | I11: Secretaria | J11: Supervisor | K11: Supervisor Matriz | L11: 252305 | M11: Avaliação de tempos real | N11: Elegível | O11: NAO ELEGIVEL COTA APRENDIZ | P11: CLT | Q11: Preponderante | R11: Elementares | S11: Supervisionam equipes de trabalho a assessor os executivos no desempenho de suas funções, geram suprimentos e gerencia informações, garantindo o apoio pela equipe a Diretoria Executiva no que tange a atividades de secretaria,como, agendamento de compromissos, atendimentos telefonico | T11: IE.26.005.P31 | U11: IE.26.005.P31
A12: HOLDING | B12: HOLDING | C12: 6110336 | D12: ANALISTA SUPORTE EXECUTIVO SR | E12: 8 | F12: ATIVO | G12: Corporativo | H12: Administração & Serviços | I12: Secretaria | J12: Analista | K12: Analista Sr | L12: 142330 | M12: Avaliação de tempos real | N12: Elegível | O12: NAO ELEGIVEL COTA APRENDIZ | P12: CLT | Q12: Preponderante | R12: Elementares | S12: Apoiar a Diretoria Executiva no que tange a atividades de secretaria, como, agendamento de compromissos, atendimentos telefonico e afins. | T12: IE.26.005.P21 | U12: IE.26.005.P21
A13: HOLDING | B13: HOLDING | C13: 6110335 | D13: ANALISTA SUPORTE EXECUTIVO PL | E13: 6 | F13: ATIVO | G13: Corporativo | H13: Administração & Serviços | I13: Secretaria | J13: Analista | K13: Analista Pl | L13: 142330 | M13: Avaliação de tempos real | N13: Elegível | O13: NAO ELEGIVEL COTA APRENDIZ | P13: CLT | Q13: Preponderante | R13: Elementares | S13: Apoiar a Diretoria Executiva no que tange a atividades de secretaria, como, agendamento de compromissos, atendimentos telefonico e afins. | T13: IE.26.005.P11 | U13: IE.26.005.P11
... A49: HOLDING | B49: HOLDING | C49: 6103579 | D49: ASSISTENTE ADMINISTRATIVO II | E49: 5 | F49: ATIVO | G49: Corporativo | H49: Administração & Serviços | I49: Serviços administrativos | J49: Assistente | K49: Assistente | L49: 411010 | M49: Avaliação de tempos real | N49: Elegível | O49: ELEGIVEL COTA APRENDIZ | P49: CLT | Q49: Preponderante | R49: Elementares | S49: Executar servicos de apoio as diversas areas da Organizacao atendem fornecedores e clientes, fornecendo e recebendo informacoes sobre produtos e servicos tratam de documentos variados, cumprindo todo o procedimento necessario referente aos mesmos. | T49: IE.26.002.S20 | U49: IE.26.002.S20
A50: HOLDING | B50: HOLDING | C50: 6103578 | D50: ASSISTENTE ADMINISTRATIVO I | E50: 4 | F50: ATIVO | G50: Corporativo | H50: Administração & Serviços | I50: Serviços administrativos | J50: Assistente | K50: Assistente | L50: 411010 | M50: Avaliação de tempos real | N50: Elegível | O50: ELEGIVEL COTA APRENDIZ | P50: CLT | Q50: Preponderante | R50: Elementares | S50: Executar servicos de apoio as diversas areas da Organizacao atendem fornecedores e clientes, fornecendo e recebendo informacoes sobre produtos e servicos tratam de documentos variados, cumprindo todo o procedimento necessario referente aos mesmos.
A51: HOLDING | B51: HOLDING | C51: 6102344 | D51: AUXILIAR ADMINISTRATIVO | E51: 2 | F51: ATIVO | G51: Corporativo | H51: Administração & Serviços | I51: Serviços administrativos | J51: Auxiliar | K51: Auxiliar | L51: 411010 | M51: Avaliação de tempos real | N51: Elegível | O51: ELEGIVEL COTA APRENDIZ | P51: CLT | Q51: Preponderante | R51: Elementares | S51: Prestar suporte a equipe, sob supervisao, realizando atividades administrativas, visando assegurar o cumprimento das normas e procedimentos internos. | T51: IE.26.002.S10 | U51: IE.26.002.S10
A52: MEDSERVICE | B52: MEDSERVICE | C52: 10209227 | D52: ASSISTENTE ADMINISTRATIVO III | E52: 6 | F52: ATIVO | G52: Corporativo | H52: Administração & Serviços | I52: Serviços administrativos | J52: Assistente | K52: Assistente | L52: 411010 | M52: Avaliação de tempos real | N52: Elegível | O52: ELEGIVEL COTA APRENDIZ | P52: CLT | Q52: Preponderante | R52: Saúde | S52: Executar servicos de apoio as diversas areas da Organizacao atendem fornecedores e clientes, fornecendo e recebendo informacoes sobre produtos e servicos tratam de documentos variados, cumprindo todo o procedimento necessario referente aos mesmos. | T52: IE.26.002.S20 | U52: IE.26.002.S20
A53: MEDSERVICE | B53: MEDSERVICE | C53: 10203579 | D53: ASSISTENTE ADMINISTRATIVO II | E53: 5 | F53: ATIVO | G53: Corporativo | H53: Administração & Serviços | I53: Serviços administrativos | J53: Assistente | K53: Assistente | L53: 411010 | M53: Avaliação de tempos real | N53: Elegível | O53: ELEGIVEL COTA APRENDIZ | P53: CLT | Q53: Preponderante | R53: Saúde | S53: Executar servicos de apoio as diversas areas da Organizacao atendem fornecedores e clientes, fornecendo e recebendo informacoes sobre produtos e servicos tratam de documentos variados, cumprindo todo o procedimento necessario referente aos mesmos. | T53: IE.26.002.S20 | U53: IE.26.002.S20
A54: MEDSERVICE | B54: MEDSERVICE | C54: 10203578 | D54: ASSISTENTE ADMINISTRATIVO I | E54: 4 | F54: ATIVO | G54: Corporativo | H54: Administração & Serviços | I54: Serviços administrativos | J54: Assistente | K54: Assistente | L54: 411010 | M54: Avaliação de tempos real | N54: Elegível | O54: ELEGIVEL COTA APRENDIZ | P54: CLT | Q54: Preponderante | R54: Saúde | S54: Executar servicos de apoio as diversas areas da Organizacao atendem fornecedores e clientes, fornecendo e recebendo informacoes sobre produtos e servicos tratam de documentos variados, cumprindo todo o procedimento necessario referente aos mesmos. | T54: IE.26.002.S20 | U54: IE.26.002.S20
A55: MEDSERVICE | B55: MEDSERVICE | C55: 10202344 | D55: AUXILIAR ADMINISTRATIVO | E55: 2 | F55: ATIVO | G55: Corporativo | H55: Administração & Serviços | I55: Serviços administrativos | J55: Auxiliar | K55: Auxiliar | L55: 411010 | M55: Avaliação de tempos real | N55: Elegível | O55: ELEGIVEL COTA APRENDIZ | P55: CLT | Q55: Preponderante | R55: Saúde | S55: Prestar suporte a equipe, sob supervisao, realizando atividades administrativas, visando assegurar o cumprimento das normas e procedimentos internos. | T55: IE.26.002.S10 | U55: IE.26.002.S10
A56: NOVAMED | B56: NOVAMED | C56: 11609227 | D56: ASSISTENTE ADMINISTRATIVO III | E56: 6 | F56: ATIVO | G56: Corporativo | H56: Administração & Serviços | I56: Serviços administrativos | J56: Assistente | K56: Assistente | L56: 411010 | M56: Avaliação de tempos real | N56: Elegível | O56: ELEGIVEL COTA APRENDIZ | P56: CLT | Q56: Preponderante | R56: Saúde | S56: Executar servicos de apoio as diversas areas da Organizacao atendem fornecedores e clientes, fornecendo e recebendo informacoes sobre produtos e servicos tratam de documentos variados, cumprindo todo o procedimento necessario referente aos mesmos. | T56: IE.26.002.S20 | U56: IE.26.002.S20
A57: NOVAMED | B57: NOVAMED | C57: 11603579 | D57: ASSISTENTE ADMINISTRATIVO II | E57: 5 | F57: ATIVO | G57: Corporativo | H57: Administração & Serviços | I57: Serviços administrativos | J57: Assistente | K57: Assistente | L57: 411010 | M57: Avaliação de tempos real | N57: Elegível | O57: ELEGIVEL COTA APRENDIZ | P57: CLT | Q57: Preponderante | R57: Saúde | S57: Executar servicos de apoio as diversas areas da Organizacao atendem fornecedores e clientes, fornecendo e recebendo informacoes sobre produtos e servicos tratam de documentos variados, cumprindo todo o procedimento necessario referente aos mesmos. | T57: IE.26.002.S20 | U57: IE.26.002.S20
A58: NOVAMED | B58: NOVAMED | C58: 11603578 | D58: ASSISTENTE ADMINISTRATIVO I | E58: 4 | F58: ATIVO | G58: Corporativo | H58: Administração & Serviços | I58: Serviços administrativos | J58: Assistente | K58: Assistente | L58: 411010 | M58: Avaliação de tempos real | N58: Elegível | O58: ELEGIVEL COTA APRENDIZ | P58: CLT | Q58: Preponderante | R58: Saúde | S58: Executar servicos de apoio as diversas areas da Organizacao atendem fornecedores e clientes, fornecendo e recebendo informacoes sobre produtos e servicos tratam de documentos variados, cumprindo todo o procedimento necessario referente aos mesmos. | T58: IE.26.002.S20 | U58: IE.26.002.S20
A59: NOVAMED | B59: NOVAMED | C59: 11602344 | D59: AUXILIAR ADMINISTRATIVO | E59: 2 | F59: ATIVO | G59: Corporativo | H59: Administração & Serviços | I59: Serviços administrativos | J59: Auxiliar | K59: Auxiliar | L59: 411010 | M59: Avaliação de tempos real | N59: Elegível | O59: ELEGIVEL COTA APRENDIZ | P59: CLT | Q59: Preponderante | R59: Saúde | S59: Prestar suporte a equipe, sob supervisao, realizando atividades administrativas, visando assegurar o cumprimento das normas e procedimentos internos. | T59: IE.26.002.S10 | U59: IE.26.002.S10
A60: SAUDE | B60: SAUDE | C60: 6305918 | D60: GERENTE SUPORTE ADMINISTRATIVO | E60: 11 | F60: ATIVO | G60: Corporativo | H60: Administração & Serviços | I60: Serviços administrativos | J60: GA | K60: GA | L60: 142105 | M60: Avaliação de tempos teórica | N60: Não elegível | O60: NAO ELEGIVEL COTA APRENDIZ | P60: CLT | Q60: Preponderante | R60: Saúde | S60: Gerenciar, orientar e acompanhar todas as atividades pertinentes a suaarea de responsabilidade para garantir conformidade com as normas epoliticas da Organizacao. Subsidiar a Diretoria do Departamento cominformacoes gerenciais quando necessario para falicitar a tomada dedecisao. Acompanhar os processos de eficiencia operacional eplanejamento estrategico. Assegurar que os projetos da area sejamimplementados e acompanhar os processos de melhoria continua, bem comogarantir que as operacoes estejam dentro dos padroes de qualidade eseguranca da Organizacao. | T60: IE.26.002.M30 | U60: IE.26.002.M30
A61: SAUDE | B61: SAUDE | C61: 6305883 | D61: SUPERVISOR SUPORTE ADMINISTRATIVO | E61: 8 | F61: ATIVO | G61: Corporativo | H61: Administração & Serviços | I61: Serviços administrativos | J61: Supervisor | K61: Supervisor Matriz | L61: 142105 | M61: Avaliação de tempos real | N61: Elegível | O61: NAO ELEGIVEL COTA APRENDIZ | P61: CLT | Q61: Preponderante | R61: Saúde | S61: Supervisionar e orientar a equipe sob gestao, acompanhar e administrar aexecucao das atividades operacionais e administrativas, garantindo oatendimento das responsabilidades nos prazos estipulados. | T61: IE.26.002.M10 | U61: IE.26.002.M10
A62: SAUDE | B62: SAUDE | C62: 6309227 | D62: ASSISTENTE ADMINISTRATIVO III | E62: 6 | F62: ATIVO | G62: Corporativo | H62: Administração & Serviços | I62: Serviços administrativos | J62: Assistente | K62: Assistente | L62: 411010 | M62: Avaliação de tempos real | N62: Elegível | O62: ELEGIVEL COTA APRENDIZ | P62: CLT | Q62: Preponderante | R62: Saúde | S62: Executar servicos de apoio as diversas areas da Organizacao atendemfornecedores e clientes, fornecendo e recebendo informacoes sobreprodutos e servicos tratam de documentos variados, cumprindo todo oprocedimento necessario referente aos mesmos. | T62: IE.26.002.S20 | U62: IE.26.002.S20
... A69: SAUDE | B69: SAUDE | C69: 6302726 | D69: MOTORISTA | E69: 2 | F69: ATIVO | G69: Corporativo | H69: Administração & Serviços | I69: Serviços operacionais | J69: Auxiliar | K69: Auxiliar | L69: 782305 | M69: Avaliação de tempos real | N69: Elegível | O69: ELEGIVEL COTA APRENDIZ | P69: CLT | Q69: Preponderante | R69: Saúde | S69: Dirigir, manobrar veiculos e transportar os Diretores da Organizacao,sendo responsaveis pela integridade fisica dos mesmos, alem de realizarverificacoes e manutencoes basicas do veiculo. | T69: IE.26.010.S20 | U69: IE.26.010.S20
A70: BSP | B70: IMOBILIARIA | C70: 10610537 | D70: GERENTE ARQUITETURA | E70: 11 | F70: ATIVO | G70: Negócios & operações | H70: Arquitetura & Engenharia | I70: Arquitetura | J70: GA | K70: GA | L70: 142105 | M70: Avaliação de tempos teórica | N70: Não elegível | O70: NAO ELEGIVEL COTA APRENDIZ | P70: CLT | Q70: Específico | R70: Empreendimentos | S70: Liderar as atividades das equipes sob sua gestao. Aprovar e validar osprojetos que envolvam planos de Engenharia e Arquitetura de obras daOrganizacao Bradesco. | T70: Sem matching
A71: BSP | B71: IMOBILIARIA | C71: 10609185 | D71: ARQUITETO III | E71: 10 | F71: ATIVO | G71: Negócios & operações | H71: Arquitetura & Engenharia | I71: Arquitetura | J71: Analista | K71: Analista Sr | L71: 214115 | M71: Avaliação de tempos real | N71: Elegível | O71: NAO ELEGIVEL COTA APRENDIZ | P71: CLT | Q71: Específico | R71: Empreendimentos | S71: Efetuar analises tecnicas de projetos de Arquitetura, definindo padroese materiais a serem utilizados. | T71: Sem matching
A72: BSP | B72: IMOBILIARIA | C72: 10603577 | D72: ARQUITETO II | E72: 9 | F72: ATIVO | G72: Negócios & operações | H72: Arquitetura & Engenharia | I72: Arquitetura | J72: Analista | K72: Analista Pl | L72: 214115 | M72: Avaliação de tempos real | N72: Elegível | O72: NAO ELEGIVEL COTA APRENDIZ | P72: CLT | Q72: Específico | R72: Empreendimentos | S72: Efetuar analises tecnicas de projetos de Arquitetura, definindo padroese materiais a serem utilizados.C 10603578 ASSISTENTE ADMINISTRATIVO Cargo C 10603578 ASSISTENTE ADMINISTRATIVO I | T72: Sem matching
A73: BSP | B73: IMOBILIARIA | C73: 10609190 | D73: ARQUITETO I | E73: 7 | F73: ATIVO | G73: Negócios & operações | H73: Arquitetura & Engenharia | I73: Arquitetura | J73: Analista | K73: Analista Jr | L73: 214115 | M73: Avaliação de tempos real | N73: Elegível | O73: NAO ELEGIVEL COTA APRENDIZ | P73: CLT | Q73: Específico | R73: Empreendimentos | S73: Efetuar analises tecnicas de projetos de Arquitetura, definindo padroese materiais a serem utilizados. | T73: Sem matching
A74: HOLDING | B74: HOLDING | C74: 6109187 | D74: ARQUITETO COORDENADOR | E74: 10 | F74: ATIVO | G74: Negócios & operações | H74: Arquitetura & Engenharia | I74: Arquitetura | J74: Coordenador | K74: Coordenador Matriz | L74: 214115 | M74: Avaliação de tempos real | N74: Elegível | O74: NAO ELEGIVEL COTA APRENDIZ | P74: CLT | Q74: Específico | R74: Elementares | S74: Liderar as atividades das equipes sob sua gestao. Aprova e valida os projetos que envolvam planos de Engenharia e Arquitetura de obras da Organizacao Bradesco. | T74: Sem matching
A75: HOLDING | B75: HOLDING | C75: 6103577 | D75: ARQUITETO II | E75: 9 | F75: ATIVO | G75: Negócios & operações | H75: Arquitetura & Engenharia | I75: Arquitetura | J75: Analista | K75: Analista Pl | L75: 214115 | M75: Avaliação de tempos real | N75: Elegível | O75: NAO ELEGIVEL COTA APRENDIZ | P75: CLT | Q75: Específico | R75: Elementares | S75: Efetuar analises tecnicas de projetos de Arquitetura, definindo padroes e materiais a serem utilizados. | T75: Sem matching
A76: HOLDING | B76: HOLDING | C76: 6109190 | D76: ARQUITETO I | E76: 7 | F76: ATIVO | G76: Negócios & operações | H76: Arquitetura & Engenharia | I76: Arquitetura | J76: Analista | K76: Analista Jr | L76: 214115 | M76: Avaliação de tempos real | N76: Elegível | O76: NAO ELEGIVEL COTA APRENDIZ | P76: CLT | Q76: Específico | R76: Elementares | S76: Efetuar analises tecnicas de projetos de Arquitetura, definindo padroes e materiais a serem utilizados. | T76: Sem matching
A77: BSP | B77: IMOBILIARIA | C77: 10610539 | D77: GERENTE ENGENHARIA | E77: 11 | F77: ATIVO | G77: Negócios & operações | H77: Arquitetura & Engenharia | I77: Engenharia | J77: GA | K77: GA | L77: 214215 | M77: Avaliação de tempos teórica | N77: Não elegível | O77: NAO ELEGIVEL COTA APRENDIZ | P77: CLT | Q77: Específico | R77: Empreendimentos | S77: Liderar as atividades das equipes sob sua gestao. Aprovar e validar osprojetos que envolvam planos de Engenharia e Arquitetura de obras daOrganizacao Bradesco. | T77: Sem matching
A78: BSP | B78: IMOBILIARIA | C78: 10609184 | D78: ENGENHEIRO III | E78: 10 | F78: ATIVO | G78: Negócios & operações | H78: Arquitetura & Engenharia | I78: Engenharia | J78: Analista | K78: Analista Sr | L78: 214205 | M78: Avaliação de tempos real | N78: Elegível | O78: NAO ELEGIVEL COTA APRENDIZ | P78: CLT | Q78: Específico | R78: Empreendimentos | S78: Efetuar análises técnicas de projetos de Engenharia, definindo técnicase metodologias a serem utilizadas. | T78: Sem matching
A79: BSP | B79: IMOBILIARIA | C79: 10609188 | D79: ENGENHEIRO II | E79: 9 | F79: ATIVO | G79: Negócios & operações | H79: Arquitetura & Engenharia | I79: Engenharia | J79: Analista | K79: Analista Pl | L79: 214205 | M79: Avaliação de tempos real | N79: Elegível | O79: NAO ELEGIVEL COTA APRENDIZ | P79: CLT | Q79: Específico | R79: Empreendimentos | S79: Efetuar analises tecnicas de projetos de Engenharia, definindo tecnicase metodologias a serem utilizadas. | T79: Sem matching
A80: BSP | B80: IMOBILIARIA | C80: 10603509 | D80: ENGENHEIRO I | E80: 7 | F80: ATIVO | G80: Negócios & operações | H80: Arquitetura & Engenharia | I80: Engenharia | J80: Analista | K80: Analista Jr | L80: 214205 | M80: Avaliação de tempos real | N80: Elegível | O80: NAO ELEGIVEL COTA APRENDIZ | P80: CLT | Q80: Específico | R80: Empreendimentos | S80: Efetuar analises tecnicas de projetos de Engenharia, definindo tecnicase metodologias a serem utilizadas. | T80: Sem matching
A81: BSP | B81: IMOBILIARIA | C81: 10609191 | D81: ANALISTA PROJETOS OBRAS | E81: 5 | F81: ATIVO | G81: Negócios & operações | H81: Arquitetura & Engenharia | I81: Engenharia | J81: Analista | K81: Analista Jr | L81: 312105 | M81: Avaliação de tempos real | N81: Elegível | O81: NAO ELEGIVEL COTA APRENDIZ | P81: CLT | Q81: Preponderante | R81: Empreendimentos | S81: Atuar nas tarefas administrativas da area como controlar despesas,receber documentos, organizar arquivos, gerar relatorios pertinentes aarea, com vistas a garantir e proporcionar um ambiente organizado. | T81: Sem matching
... A84: HOLDING | B84: HOLDING | C84: 6103509 | D84: ENGENHEIRO I | E84: 7 | F84: ATIVO | G84: Negócios & operações | H84: Arquitetura & Engenharia | I84: Engenharia | J84: Analista | K84: Analista Jr | L84: 214205 | M84: Avaliação de tempos real | N84: Elegível | O84: NAO ELEGIVEL COTA APRENDIZ | P84: CLT | Q84: Específico | R84: Elementares | S84: Efetuar analises tecnicas de projetos de Engenharia, definindo tecnicas e metodologias a serem utilizadas. | T84: Sem matching
A85: AFFINITY | B85: BSP AFFINITY | C85: 10011276 | D85: ESPECIALISTA ATUARIAL | E85: 12 | F85: ATIVO | G85: Negócios & operações | H85: Atuarial, modelagem e dados | I85: Atuarial | J85: GA | K85: Especialista | L85: 211105 | M85: Avaliação de tempos teórica | N85: Não elegível | O85: NAO ELEGIVEL COTA APRENDIZ | P85: CLT | Q85: Preponderante | R85: Affinity | S85: Responsavel por desenvolver o refinamento dos dados para obtenção das bases adequadas, Garantir a homologação de dados imprescindíveis Saúde, transferidos para o ADAC, Proporcionar manutenção adequada aos motores de cálculos | T85: IE.33.002.M30 | U85: IE.33.002.M30
A86: AFFINITY | B86: BSP AFFINITY | C86: 10010290 | D86: CONSULTOR ATUARIAL | E86: 11 | F86: ATIVO | G86: Negócios & operações | H86: Atuarial, modelagem e dados | I86: Atuarial | J86: Especialista | K86: Consultor | L86: 211105 | M86: Avaliação de tempos teórica | N86: Não elegível | O86: NAO ELEGIVEL COTA APRENDIZ | P86: CLT | Q86: Preponderante | R86: Affinity | S86: Apoiar no refinamento dos dados para obtenção das bases adequadas, Garantir a homologação de dados imprescindíveis, transferidos para o ADAC, Proporcionar manutenção adequada aos motores de cálculos | T86: IE.33.002.P40 | U86: IE.33.002.P40
A87: BARE | B87: AUTO RE SEG | C87: 7511276 | D87: ESPECIALISTA ATUARIAL I | E87: 12 | F87: ATIVO | G87: Negócios & operações | H87: Atuarial, modelagem e dados | I87: Atuarial | J87: GA | K87: Especialista | L87: 211105 | M87: Avaliação de tempos teórica | N87: Não elegível | O87: NAO ELEGIVEL COTA APRENDIZ | P87: CLT | Q87: Preponderante | R87: Elementares | S87: Responsavel por desenvolver o refinamento dos dados para obtenção das bases adequadas, Garantir a homologação de dados imprescindíveis Saúde, transferidos para o ADAC, Proporcionar manutenção adequada aos motores de cálculos | T87: IE.33.002.M30 | U87: IE.33.002.M30
A88: BARE | B88: AUTO RE SEG | C88: 7508849 | D88: GERENTE ATUARIAL | E88: 12 | F88: ATIVO | G88: Negócios & operações | H88: Atuarial, modelagem e dados | I88: Atuarial | J88: GA | K88: GA | L88: 211105 | M88: Avaliação de tempos teórica | N88: Não elegível | O88: NAO ELEGIVEL COTA APRENDIZ | P88: CLT | Q88: Preponderante | R88: Elementares | S88: Gerenciar a equipe referente aos calculos atuariais, analisando e revisando os trabalhos e projetos de natureza atuarial, executados pela area. | T88: IE.33.002.M30 | U88: IE.33.002.M30
A89: BARE | B89: AUTO RE SEG | C89: 7510290 | D89: CONSULTOR ATUARIAL | E89: 11 | F89: ATIVO | G89: Negócios & operações | H89: Atuarial, modelagem e dados | I89: Atuarial | J89: Especialista | K89: Consultor | L89: 211105 | M89: Avaliação de tempos teórica | N89: Não elegível | O89: NAO ELEGIVEL COTA APRENDIZ | P89: CLT | Q89: Preponderante | R89: Elementares | S89: Apoiar no refinamento dos dados para obtenção das bases adequadas, Garantir a homologação de dados imprescindíveis, transferidos para o ADAC, Proporcionar manutenção adequada aos motores de cálculos | T89: IE.33.002.P40 | U89: IE.33.002.P40
A90: BARE | B90: AUTO RE SEG | C90: 7515403 | D90: COORDENADOR ATUARIAL | E90: 11 | F90: ATIVO | G90: Negócios & operações | H90: Atuarial, modelagem e dados | I90: Atuarial | J90: Coordenador | K90: Coordenador Matriz | L90: 211105 | M90: Avaliação de tempos real | N90: Elegível | O90: NAO ELEGIVEL COTA APRENDIZ | P90: CLT | Q90: Preponderante | R90: Elementares | S90: Apoiar no refinamento dos dados para obtenção das bases adequadas, Garantir a homologação de dados imprescindíveis Saúde, transferidos para o ADAC, Proporcionar manutenção adequada aos motores de cálculos | T90: IE.33.002.M20 | U90: IE.33.002.M20
A91: BARE | B91: AUTO RE SEG | C91: 7508817 | D91: ANALISTA ATUARIAL SR | E91: 10 | F91: ATIVO | G91: Negócios & operações | H91: Atuarial, modelagem e dados | I91: Atuarial | J91: Analista | K91: Analista Sr | L91: 211105 | M91: Avaliação de tempos real | N91: Elegível | O91: NAO ELEGIVEL COTA APRENDIZ | P91: CLT | Q91: Preponderante | R91: Elementares | S91: Realizar calculos de maior complexidade relacionados as provisoes tecnicas, utilizando metodologias atuariais e estatisticas, para o trabalho de Certificacao das Provisoes Tecnicas, desenvolvimento do Fluxo das Provisoes Tecnicas e tambem no calculo de Capital Minimo Regulatorio. Alem disso, tambem desenvolve controles legais atraves de relatorios e auxilia na implementacao de projetos que visem atender as normas estabelecidas pelos orgaos reguladores. | T91: IE.33.002.P30 | U91: IE.33.002.P30
A92: BARE | B92: AUTO RE SEG | C92: 7508816 | D92: ANALISTA ATUARIAL PL | E92: 8 | F92: ATIVO | G92: Negócios & operações | H92: Atuarial, modelagem e dados | I92: Atuarial | J92: Analista | K92: Analista Pl | L92: 211105 | M92: Avaliação de tempos real | N92: Elegível | O92: NAO ELEGIVEL COTA APRENDIZ | P92: CLT | Q92: Preponderante | R92: Elementares | S92: Auxiliar os demais atuarios e o gerente da area na realizacao das atividades, no que se refere manipulacao de base de dados, otimizacao de planilhas via VBA (Visual Basic For Aplications), execucao de programas no aplicativo SAS e/ou sistemas atuariais (RAFM/MoSes). Suporte na preparacao de relatorios e analise de indicadores atuariais. | T92: IE.33.002.P30 | U92: IE.33.002.P30
A93: BARE | B93: AUTO RE SEG | C93: 7508815 | D93: ANALISTA ATUARIAL JR | E93: 6 | F93: ATIVO | G93: Negócios & operações | H93: Atuarial, modelagem e dados | I93: Atuarial | J93: Analista | K93: Analista Jr | L93: 211105 | M93: Avaliação de tempos real | N93: Elegível | O93: NAO ELEGIVEL COTA APRENDIZ | P93: CLT | Q93: Preponderante | R93: Elementares | S93: Auxiliar os demais atuarios e o gerente da area na realizacao das atividades, no que se refere manipulacao de base de dados, otimizacao de planilhas via VBA (Visual Basic For Aplications), execucao de programas no aplicativo SAS e/ou sistemas atuariais (RAFM/MoSes). Suporte na preparacao de relatorios e analise de indicadores atuariais. | T93: IE.33.002.P20 | U93: IE.33.002.P20
A94: BARE | B94: AUTO RE SEG | C94: 7510200 | D94: ANALISTA ASSISTENTE ATUARIAL | E94: 4 | F94: ATIVO | G94: Negócios & operações | H94: Atuarial, modelagem e dados | I94: Atuarial | J94: Assistente | K94: Assistente | L94: 211105 | M94: Avaliação de tempos real | N94: Elegível | O94: NAO ELEGIVEL COTA APRENDIZ | P94: CLT | Q94: Preponderante | R94: Elementares | S94: Realizar calculos de maior complexidade relacionados as provisoes tecnicas, utilizando metodologias atuariais e estatisticas, para o trabalho de Certificacao das Provisoes Tecnicas, desenvolvimento do Fluxo das Provisoes Tecnicas e tambem no calculo de Capital Minimo Regulatorio. Alem disso, tambem desenvolve controles legais atraves de relatorios e auxilia na implementacao de projetos que visem atender as normas estabelecidas pelos orgaos reguladores. | T94: IE.26.002.S20 | U94: IE.26.002.S20
A95: BSP | B95: IMOBILIARIA | C95: 10611276 | D95: ESPECIALISTA ATUARIAL | E95: 12 | F95: ATIVO | G95: Negócios & operações | H95: Atuarial, modelagem e dados | I95: Atuarial | J95: GA | K95: Especialista | L95: 211105 | M95: Avaliação de tempos teórica | N95: Não elegível | O95: NAO ELEGIVEL COTA APRENDIZ | P95: CLT | Q95: Preponderante | R95: Empreendimentos | S95: Responsavel por desenvolver o refinamento dos dados para obtenção das bases adequadas, Garantir a homologação de dados imprescindíveis Saúde, transferidos para o ADAC, Proporcionar manutenção adequada aos motores de cálculos | T95: IE.33.002.M30 | U95: IE.33.002.M30
A96: BSP | B96: IMOBILIARIA | C96: 10610290 | D96: CONSULTOR ATUARIAL | E96: 11 | F96: ATIVO | G96: Negócios & operações | H96: Atuarial, modelagem e dados | I96: Atuarial | J96: Especialista | K96: Consultor | L96: 211105 | M96: Avaliação de tempos teórica | N96: Não elegível | O96: NAO ELEGIVEL COTA APRENDIZ | P96: CLT | Q96: Preponderante | R96: Empreendimentos | S96: Apoiar no refinamento dos dados para obtenção das bases adequadas, Garantir a homologação de dados imprescindíveis, transferidos para o ADAC, Proporcionar manutenção adequada aos motores de cálculos | T96: IE.33.002.P40 | U96: IE.33.002.P40
... A195: BARE | B195: AUTO RE SEG | C195: 7510212 | D195: ANALISTA ASSISTENTE INFO GERENCIAIS | E195: 4 | F195: ATIVO | G195: Negócios & operações | H195: Atuarial, modelagem e dados | I195: Informações Gerenciais | J195: Assistente | K195: Assistente | L195: 142330 | M195: Avaliação de tempos real | N195: Elegível | O195: NAO ELEGIVEL COTA APRENDIZ | P195: CLT | Q195: Preponderante | R195: Elementares | S195: Elaborar relatorios estatisticos e indicadores, realizar analise tecnica e comparativa visando subsidiar as areas no acompanhamento e otimizacao da gestao administrativa, alinhados com o planejamento estrategico da Organizacao. Participar de grupos de trabalho, propor e auxiliar na implantacao de melhoria para o desenvolvimento de ferramentas de apoio a geracao da informacao, em atividades relacionadas a estrategia. | T195: TI.01.004.S20 | U195: TI.01.004.S20

Sheet KPIs Executivos
A1: DASHBOARD – CARGOS GBS
A2: Visão Executiva de KPIs
A4: Total de Cargos | C4: Cargos Ativos | E4: Cargos Inativos
A5: =CONT.VALORES(Dados!A2:A195) | C5: =CONT.SE(Dados!F2:F195,"ATIVO") | E5: =CONT.SE(Dados!F2:F195,"INATIVO")
C6: =CONT.SE(Dados!F2:F195,"ATIVO")/CONT.VALORES(Dados!A2:A195) | E6: =CONT.SE(Dados!F2:F195,"INATIVO")/CONT.VALORES(Dados!A2:A195)
A8: Total de Empresas | C8: Famílias GBS | E8: Grupos Hierárquicos
A9: =CONT.VALORES(ÚNICO(Dados!A2:A195)) | C9: =CONT.VALORES(ÚNICO(Dados!H2:H195)) | E9: =CONT.VALORES(ÚNICO(Dados!J2:J195))
A12: Sem Cod. Mercer 2026 | C12: Corporativo | E12: Negócios & Operações
A13: =CONT.SE(Dados!U2:U195,"") | C13: =CONT.SE(Dados!G2:G195,"Corporativo") | E13: =CONT.SE(Dados!G2:G195,"Negócios & operações")
A14: =CONT.SE(Dados!U2:U195,"")/CONT.VALORES(Dados!A2:A195) | C14: =CONT.SE(Dados!G2:G195,"Corporativo")/CONT.VALORES(Dados!A2:A195) | E14: =CONT.SE(Dados!G2:G195,"Negócios & operações")/CONT.VALORES(Dados!A2:A195)

Sheet Distribuição por Grade
A1: Distribuição de Cargos por Grade
A2: Grade | B2: Ativos | C2: Inativos | D2: Total | E2: % do Total
A3: 2 | B3: =CONT.SES(Dados!E$2:E$195,A3,Dados!F$2:F$195,"ATIVO") | C3: =CONT.SES(Dados!E$2:E$195,A3,Dados!F$2:F$195,"INATIVO") | D3: =B3+C3 | E3: =D3/CONT.VALORES(Dados!A$2:A$195)
A4: 4 | B4: =CONT.SES(Dados!E$2:E$195,A4,Dados!F$2:F$195,"ATIVO") | C4: =CONT.SES(Dados!E$2:E$195,A4,Dados!F$2:F$195,"INATIVO") | D4: =B4+C4 | E4: =D4/CONT.VALORES(Dados!A$2:A$195)
A5: 5 | B5: =CONT.SES(Dados!E$2:E$195,A5,Dados!F$2:F$195,"ATIVO") | C5: =CONT.SES(Dados!E$2:E$195,A5,Dados!F$2:F$195,"INATIVO") | D5: =B5+C5 | E5: =D5/CONT.VALORES(Dados!A$2:A$195)
A6: 6 | B6: =CONT.SES(Dados!E$2:E$195,A6,Dados!F$2:F$195,"ATIVO") | C6: =CONT.SES(Dados!E$2:E$195,A6,Dados!F$2:F$195,"INATIVO") | D6: =B6+C6 | E6: =D6/CONT.VALORES(Dados!A$2:A$195)
A7: 7 | B7: =CONT.SES(Dados!E$2:E$195,A7,Dados!F$2:F$195,"ATIVO") | C7: =CONT.SES(Dados!E$2:E$195,A7,Dados!F$2:F$195,"INATIVO") | D7: =B7+C7 | E7: =D7/CONT.VALORES(Dados!A$2:A$195)
A8: 8 | B8: =CONT.SES(Dados!E$2:E$195,A8,Dados!F$2:F$195,"ATIVO") | C8: =CONT.SES(Dados!E$2:E$195,A8,Dados!F$2:F$195,"INATIVO") | D8: =B8+C8 | E8: =D8/CONT.VALORES(Dados!A$2:A$195)
A9: 9 | B9: =CONT.SES(Dados!E$2:E$195,A9,Dados!F$2:F$195,"ATIVO") | C9: =CONT.SES(Dados!E$2:E$195,A9,Dados!F$2:F$195,"INATIVO") | D9: =B9+C9 | E9: =D9/CONT.VALORES(Dados!A$2:A$195)
A10: 10 | B10: =CONT.SES(Dados!E$2:E$195,A10,Dados!F$2:F$195,"ATIVO") | C10: =CONT.SES(Dados!E$2:E$195,A10,Dados!F$2:F$195,"INATIVO") | D10: =B10+C10 | E10: =D10/CONT.VALORES(Dados!A$2:A$195)
A11: 11 | B11: =CONT.SES(Dados!E$2:E$195,A11,Dados!F$2:F$195,"ATIVO") | C11: =CONT.SES(Dados!E$2:E$195,A11,Dados!F$2:F$195,"INATIVO") | D11: =B11+C11 | E11: =D11/CONT.VALORES(Dados!A$2:A$195)
A12: 12 | B12: =CONT.SES(Dados!E$2:E$195,A12,Dados!F$2:F$195,"ATIVO") | C12: =CONT.SES(Dados!E$2:E$195,A12,Dados!F$2:F$195,"INATIVO") | D12: =B12+C12 | E12: =D12/CONT.VALORES(Dados!A$2:A$195)
A13: 13 | B13: =CONT.SES(Dados!E$2:E$195,A13,Dados!F$2:F$195,"ATIVO") | C13: =CONT.SES(Dados!E$2:E$195,A13,Dados!F$2:F$195,"INATIVO") | D13: =B13+C13 | E13: =D13/CONT.VALORES(Dados!A$2:A$195)
A14: TOTAL | B14: =SOMA(B3:B13) | C14: =SOMA(C3:C13) | D14: =SOMA(D3:D13) | E14: =SOMA(E3:E13)

Sheet Análise por Família GBS
A1: Análise por Família GBS × Grupo Hierárquico
A2: Família GBS | B2: Sub Família | C2: GA | D2: GS | E2: Coordenador | F2: Supervisor | G2: Especialista | H2: Analista | I2: Assistente | J2: Auxiliar | K2: TOTAL
A3: Administração & Serviços | B3: Facilities e Serviços Gerais | C3: =CONT.SES(Dados!H$2:H$195,"Administração & Serviços",Dados!I$2:I$195,"Facilities e Serviços Gerais",Dados!J$2:J$195,"GA") | D3: =CONT.SES(Dados!H$2:H$195,"Administração & Serviços",Dados!I$2:I$195,"Facilities e Serviços Gerais",Dados!J$2:J$195,"GS") | E3: =CONT.SES(Dados!H$2:H$195,"Administração & Serviços",Dados!I$2:I$195,"Facilities e Serviços Gerais",Dados!J$2:J$195,"Coordenador") | F3: =CONT.SES(Dados!H$2:H$195,"Administração & Serviços",Dados!I$2:I$195,"Facilities e Serviços Gerais",Dados!J$2:J$195,"Supervisor") | G3: =CONT.SES(Dados!H$2:H$195,"Administração & Serviços",Dados!I$2:I$195,"Facilities e Serviços Gerais",Dados!J$2:J$195,"Especialista") | H3: =CONT.SES(Dados!H$2:H$195,"Administração & Serviços",Dados!I$2:I$195,"Facilities e Serviços Gerais",Dados!J$2:J$195,"Analista") | I3: =CONT.SES(Dados!H$2:H$195,"Administração & Serviços",Dados!I$2:I$195,"Facilities e Serviços Gerais",Dados!J$2:J$195,"Assistente") | J3: =CONT.SES(Dados!H$2:H$195,"Administração & Serviços",Dados!I$2:I$195,"Facilities e Serviços Gerais",Dados!J$2:J$195,"Auxiliar") | K3: =SOMA(C3:J3)
B4: Secretaria | C4: =CONT.SES(Dados!H$2:H$195,"Administração & Serviços",Dados!I$2:I$195,"Secretaria",Dados!J$2:J$195,"GA") | D4: =CONT.SES(Dados!H$2:H$195,"Administração & Serviços",Dados!I$2:I$195,"Secretaria",Dados!J$2:J$195,"GS") | E4: =CONT.SES(Dados!H$2:H$195,"Administração & Serviços",Dados!I$2:I$195,"Secretaria",Dados!J$2:J$195,"Coordenador") | F4: =CONT.SES(Dados!H$2:H$195,"Administração & Serviços",Dados!I$2:I$195,"Secretaria",Dados!J$2:J$195,"Supervisor") | G4: =CONT.SES(Dados!H$2:H$195,"Administração & Serviços",Dados!I$2:I$195,"Secretaria",Dados!J$2:J$195,"Especialista") | H4: =CONT.SES(Dados!H$2:H$195,"Administração & Serviços",Dados!I$2:I$195,"Secretaria",Dados!J$2:J$195,"Analista") | I4: =CONT.SES(Dados!H$2:H$195,"Administração & Serviços",Dados!I$2:I$195,"Secretaria",Dados!J$2:J$195,"Assistente") | J4: =CONT.SES(Dados!H$2:H$195,"Administração & Serviços",Dados!I$2:I$195,"Secretaria",Dados!J$2:J$195,"Auxiliar") | K4: =SOMA(C4:J4)
B5: Serviços administrativos | C5: =CONT.SES(Dados!H$2:H$195,"Administração & Serviços",Dados!I$2:I$195,"Serviços administrativos",Dados!J$2:J$195,"GA") | D5: =CONT.SES(Dados!H$2:H$195,"Administração & Serviços",Dados!I$2:I$195,"Serviços administrativos",Dados!J$2:J$195,"GS") | E5: =CONT.SES(Dados!H$2:H$195,"Administração & Serviços",Dados!I$2:I$195,"Serviços administrativos",Dados!J$2:J$195,"Coordenador") | F5: =CONT.SES(Dados!H$2:H$195,"Administração & Serviços",Dados!I$2:I$195,"Serviços administrativos",Dados!J$2:J$195,"Supervisor") | G5: =CONT.SES(Dados!H$2:H$195,"Administração & Serviços",Dados!I$2:I$195,"Serviços administrativos",Dados!J$2:J$195,"Especialista") | H5: =CONT.SES(Dados!H$2:H$195,"Administração & Serviços",Dados!I$2:I$195,"Serviços administrativos",Dados!J$2:J$195,"Analista") | I5: =CONT.SES(Dados!H$2:H$195,"Administração & Serviços",Dados!I$2:I$195,"Serviços administrativos",Dados!J$2:J$195,"Assistente") | J5: =CONT.SES(Dados!H$2:H$195,"Administração & Serviços",Dados!I$2:I$195,"Serviços administrativos",Dados!J$2:J$195,"Auxiliar") | K5: =SOMA(C5:J5)
B6: Serviços operacionais | C6: =CONT.SES(Dados!H$2:H$195,"Administração & Serviços",Dados!I$2:I$195,"Serviços operacionais",Dados!J$2:J$195,"GA") | D6: =CONT.SES(Dados!H$2:H$195,"Administração & Serviços",Dados!I$2:I$195,"Serviços operacionais",Dados!J$2:J$195,"GS") | E6: =CONT.SES(Dados!H$2:H$195,"Administração & Serviços",Dados!I$2:I$195,"Serviços operacionais",Dados!J$2:J$195,"Coordenador") | F6: =CONT.SES(Dados!H$2:H$195,"Administração & Serviços",Dados!I$2:I$195,"Serviços operacionais",Dados!J$2:J$195,"Supervisor") | G6: =CONT.SES(Dados!H$2:H$195,"Administração & Serviços",Dados!I$2:I$195,"Serviços operacionais",Dados!J$2:J$195,"Especialista") | H6: =CONT.SES(Dados!H$2:H$195,"Administração & Serviços",Dados!I$2:I$195,"Serviços operacionais",Dados!J$2:J$195,"Analista") | I6: =CONT.SES(Dados!H$2:H$195,"Administração & Serviços",Dados!I$2:I$195,"Serviços operacionais",Dados!J$2:J$195,"Assistente") | J6: =CONT.SES(Dados!H$2:H$195,"Administração & Serviços",Dados!I$2:I$195,"Serviços operacionais",Dados!J$2:J$195,"Auxiliar") | K6: =SOMA(C6:J6)
A7: Subtotal – Administração & Serviços | C7: =SOMA(C3:C6) | D7: =SOMA(D3:D6) | E7: =SOMA(E3:E6) | F7: =SOMA(F3:F6) | G7: =SOMA(G3:G6) | H7: =SOMA(H3:H6) | I7: =SOMA(I3:I6) | J7: =SOMA(J3:J6) | K7: =SOMA(C7:J7)
A8: Arquitetura & Engenharia | B8: Arquitetura | C8: =CONT.SES(Dados!H$2:H$195,"Arquitetura & Engenharia",Dados!I$2:I$195,"Arquitetura",Dados!J$2:J$195,"GA") | D8: =CONT.SES(Dados!H$2:H$195,"Arquitetura & Engenharia",Dados!I$2:I$195,"Arquitetura",Dados!J$2:J$195,"GS") | E8: =CONT.SES(Dados!H$2:H$195,"Arquitetura & Engenharia",Dados!I$2:I$195,"Arquitetura",Dados!J$2:J$195,"Coordenador") | F8: =CONT.SES(Dados!H$2:H$195,"Arquitetura & Engenharia",Dados!I$2:I$195,"Arquitetura",Dados!J$2:J$195,"Supervisor") | G8: =CONT.SES(Dados!H$2:H$195,"Arquitetura & Engenharia",Dados!I$2:I$195,"Arquitetura",Dados!J$2:J$195,"Especialista") | H8: =CONT.SES(Dados!H$2:H$195,"Arquitetura & Engenharia",Dados!I$2:I$195,"Arquitetura",Dados!J$2:J$195,"Analista") | I8: =CONT.SES(Dados!H$2:H$195,"Arquitetura & Engenharia",Dados!I$2:I$195,"Arquitetura",Dados!J$2:J$195,"Assistente") | J8: =CONT.SES(Dados!H$2:H$195,"Arquitetura & Engenharia",Dados!I$2:I$195,"Arquitetura",Dados!J$2:J$195,"Auxiliar") | K8: =SOMA(C8:J8)
B9: Engenharia | C9: =CONT.SES(Dados!H$2:H$195,"Arquitetura & Engenharia",Dados!I$2:I$195,"Engenharia",Dados!J$2:J$195,"GA") | D9: =CONT.SES(Dados!H$2:H$195,"Arquitetura & Engenharia",Dados!I$2:I$195,"Engenharia",Dados!J$2:J$195,"GS") | E9: =CONT.SES(Dados!H$2:H$195,"Arquitetura & Engenharia",Dados!I$2:I$195,"Engenharia",Dados!J$2:J$195,"Coordenador") | F9: =CONT.SES(Dados!H$2:H$195,"Arquitetura & Engenharia",Dados!I$2:I$195,"Engenharia",Dados!J$2:J$195,"Supervisor") | G9: =CONT.SES(Dados!H$2:H$195,"Arquitetura & Engenharia",Dados!I$2:I$195,"Engenharia",Dados!J$2:J$195,"Especialista") | H9: =CONT.SES(Dados!H$2:H$195,"Arquitetura & Engenharia",Dados!I$2:I$195,"Engenharia",Dados!J$2:J$195,"Analista") | I9: =CONT.SES(Dados!H$2:H$195,"Arquitetura & Engenharia",Dados!I$2:I$195,"Engenharia",Dados!J$2:J$195,"Assistente") | J9: =CONT.SES(Dados!H$2:H$195,"Arquitetura & Engenharia",Dados!I$2:I$195,"Engenharia",Dados!J$2:J$195,"Auxiliar") | K9: =SOMA(C9:J9)
A10: Subtotal – Arquitetura & Engenharia | C10: =SOMA(C8:C9) | D10: =SOMA(D8:D9) | E10: =SOMA(E8:E9) | F10: =SOMA(F8:F9) | G10: =SOMA(G8:G9) | H10: =SOMA(H8:H9) | I10: =SOMA(I8:I9) | J10: =SOMA(J8:J9) | K10: =SOMA(C10:J10)
A11: Atuarial, modelagem e dados | B11: Atuarial | C11: =CONT.SES(Dados!H$2:H$195,"Atuarial, modelagem e dados",Dados!I$2:I$195,"Atuarial",Dados!J$2:J$195,"GA") | D11: =CONT.SES(Dados!H$2:H$195,"Atuarial, modelagem e dados",Dados!I$2:I$195,"Atuarial",Dados!J$2:J$195,"GS") | E11: =CONT.SES(Dados!H$2:H$195,"Atuarial, modelagem e dados",Dados!I$2:I$195,"Atuarial",Dados!J$2:J$195,"Coordenador") | F11: =CONT.SES(Dados!H$2:H$195,"Atuarial, modelagem e dados",Dados!I$2:I$195,"Atuarial",Dados!J$2:J$195,"Supervisor") | G11: =CONT.SES(Dados!H$2:H$195,"Atuarial, modelagem e dados",Dados!I$2:I$195,"Atuarial",Dados!J$2:J$195,"Especialista") | H11: =CONT.SES(Dados!H$2:H$195,"Atuarial, modelagem e dados",Dados!I$2:I$195,"Atuarial",Dados!J$2:J$195,"Analista") | I11: =CONT.SES(Dados!H$2:H$195,"Atuarial, modelagem e dados",Dados!I$2:I$195,"Atuarial",Dados!J$2:J$195,"Assistente") | J11: =CONT.SES(Dados!H$2:H$195,"Atuarial, modelagem e dados",Dados!I$2:I$195,"Atuarial",Dados!J$2:J$195,"Auxiliar") | K11: =SOMA(C11:J11)
B12: Ciência de Dados | C12: =CONT.SES(Dados!H$2:H$195,"Atuarial, modelagem e dados",Dados!I$2:I$195,"Ciência de Dados",Dados!J$2:J$195,"GA") | D12: =CONT.SES(Dados!H$2:H$195,"Atuarial, modelagem e dados",Dados!I$2:I$195,"Ciência de Dados",Dados!J$2:J$195,"GS") | E12: =CONT.SES(Dados!H$2:H$195,"Atuarial, modelagem e dados",Dados!I$2:I$195,"Ciência de Dados",Dados!J$2:J$195,"Coordenador") | F12: =CONT.SES(Dados!H$2:H$195,"Atuarial, modelagem e dados",Dados!I$2:I$195,"Ciência de Dados",Dados!J$2:J$195,"Supervisor") | G12: =CONT.SES(Dados!H$2:H$195,"Atuarial, modelagem e dados",Dados!I$2:I$195,"Ciência de Dados",Dados!J$2:J$195,"Especialista") | H12: =CONT.SES(Dados!H$2:H$195,"Atuarial, modelagem e dados",Dados!I$2:I$195,"Ciência de Dados",Dados!J$2:J$195,"Analista") | I12: =CONT.SES(Dados!H$2:H$195,"Atuarial, modelagem e dados",Dados!I$2:I$195,"Ciência de Dados",Dados!J$2:J$195,"Assistente") | J12: =CONT.SES(Dados!H$2:H$195,"Atuarial, modelagem e dados",Dados!I$2:I$195,"Ciência de Dados",Dados!J$2:J$195,"Auxiliar") | K12: =SOMA(C12:J12)
B13: Informações Gerenciais | C13: =CONT.SES(Dados!H$2:H$195,"Atuarial, modelagem e dados",Dados!I$2:I$195,"Informações Gerenciais",Dados!J$2:J$195,"GA") | D13: =CONT.SES(Dados!H$2:H$195,"Atuarial, modelagem e dados",Dados!I$2:I$195,"Informações Gerenciais",Dados!J$2:J$195,"GS") | E13: =CONT.SES(Dados!H$2:H$195,"Atuarial, modelagem e dados",Dados!I$2:I$195,"Informações Gerenciais",Dados!J$2:J$195,"Coordenador") | F13: =CONT.SES(Dados!H$2:H$195,"Atuarial, modelagem e dados",Dados!I$2:I$195,"Informações Gerenciais",Dados!J$2:J$195,"Supervisor") | G13: =CONT.SES(Dados!H$2:H$195,"Atuarial, modelagem e dados",Dados!I$2:I$195,"Informações Gerenciais",Dados!J$2:J$195,"Especialista") | H13: =CONT.SES(Dados!H$2:H$195,"Atuarial, modelagem e dados",Dados!I$2:I$195,"Informações Gerenciais",Dados!J$2:J$195,"Analista") | I13: =CONT.SES(Dados!H$2:H$195,"Atuarial, modelagem e dados",Dados!I$2:I$195,"Informações Gerenciais",Dados!J$2:J$195,"Assistente") | J13: =CONT.SES(Dados!H$2:H$195,"Atuarial, modelagem e dados",Dados!I$2:I$195,"Informações Gerenciais",Dados!J$2:J$195,"Auxiliar") | K13: =SOMA(C13:J13)
A14: Subtotal – Atuarial, modelagem e dados | C14: =SOMA(C11:C13) | D14: =SOMA(D11:D13) | E14: =SOMA(E11:E13) | F14: =SOMA(F11:F13) | G14: =SOMA(G11:G13) | H14: =SOMA(H11:H13) | I14: =SOMA(I11:I13) | J14: =SOMA(J11:J13) | K14: =SOMA(C14:J14)
A15: Privacidade de dados | B15: Privacidade de dados | C15: =CONT.SES(Dados!H$2:H$195,"Privacidade de dados",Dados!I$2:I$195,"Privacidade de dados",Dados!J$2:J$195,"GA") | D15: =CONT.SES(Dados!H$2:H$195,"Privacidade de dados",Dados!I$2:I$195,"Privacidade de dados",Dados!J$2:J$195,"GS") | E15: =CONT.SES(Dados!H$2:H$195,"Privacidade de dados",Dados!I$2:I$195,"Privacidade de dados",Dados!J$2:J$195,"Coordenador") | F15: =CONT.SES(Dados!H$2:H$195,"Privacidade de dados",Dados!I$2:I$195,"Privacidade de dados",Dados!J$2:J$195,"Supervisor") | G15: =CONT.SES(Dados!H$2:H$195,"Privacidade de dados",Dados!I$2:I$195,"Privacidade de dados",Dados!J$2:J$195,"Especialista") | H15: =CONT.SES(Dados!H$2:H$195,"Privacidade de dados",Dados!I$2:I$195,"Privacidade de dados",Dados!J$2:J$195,"Analista") | I15: =CONT.SES(Dados!H$2:H$195,"Privacidade de dados",Dados!I$2:I$195,"Privacidade de dados",Dados!J$2:J$195,"Assistente") | J15: =CONT.SES(Dados!H$2:H$195,"Privacidade de dados",Dados!I$2:I$195,"Privacidade de dados",Dados!J$2:J$195,"Auxiliar") | K15: =SOMA(C15:J15)
A16: Subtotal – Privacidade de dados | C16: =SOMA(C15:C15) | D16: =SOMA(D15:D15) | E16: =SOMA(E15:E15) | F16: =SOMA(F15:F15) | G16: =SOMA(G15:G15) | H16: =SOMA(H15:H15) | I16: =SOMA(I15:I15) | J16: =SOMA(J15:J15) | K16: =SOMA(C16:J16)
A17: TOTAL GERAL | C17: =CONT.SES(Dados!J$2:J$195,"GA") | D17: =CONT.SES(Dados!J$2:J$195,"GS") | E17: =CONT.SES(Dados!J$2:J$195,"Coordenador") | F17: =CONT.SES(Dados!J$2:J$195,"Supervisor") | G17: =CONT.SES(Dados!J$2:J$195,"Especialista") | H17: =CONT.SES(Dados!J$2:J$195,"Analista") | I17: =CONT.SES(Dados!J$2:J$195,"Assistente") | J17: =CONT.SES(Dados!J$2:J$195,"Auxiliar") | K17: =SOMA(C17:J17)

Sheet Análise por Empresa
A1: Análise por Empresa
A2: Empresa | B2: Total Cargos | C2: Ativos | D2: Inativos | E2: % Ativo
A3: AFFINITY | B3: =CONT.SE(Dados!A$2:A$195,"AFFINITY") | C3: =CONT.SES(Dados!A$2:A$195,"AFFINITY",Dados!F$2:F$195,"ATIVO") | D3: =CONT.SES(Dados!A$2:A$195,"AFFINITY",Dados!F$2:F$195,"INATIVO") | E3: =SE(B3>0,C3/B3,0)
A4: BARE | B4: =CONT.SE(Dados!A$2:A$195,"BARE") | C4: =CONT.SES(Dados!A$2:A$195,"BARE",Dados!F$2:F$195,"ATIVO") | D4: =CONT.SES(Dados!A$2:A$195,"BARE",Dados!F$2:F$195,"INATIVO") | E4: =SE(B4>0,C4/B4,0)
A5: BSP | B5: =CONT.SE(Dados!A$2:A$195,"BSP") | C5: =CONT.SES(Dados!A$2:A$195,"BSP",Dados!F$2:F$195,"ATIVO") | D5: =CONT.SES(Dados!A$2:A$195,"BSP",Dados!F$2:F$195,"INATIVO") | E5: =SE(B5>0,C5/B5,0)
A6: BVP | B6: =CONT.SE(Dados!A$2:A$195,"BVP") | C6: =CONT.SES(Dados!A$2:A$195,"BVP",Dados!F$2:F$195,"ATIVO") | D6: =CONT.SES(Dados!A$2:A$195,"BVP",Dados!F$2:F$195,"INATIVO") | E6: =SE(B6>0,C6/B6,0)
A7: CAP | B7: =CONT.SE(Dados!A$2:A$195,"CAP") | C7: =CONT.SES(Dados!A$2:A$195,"CAP",Dados!F$2:F$195,"ATIVO") | D7: =CONT.SES(Dados!A$2:A$195,"CAP",Dados!F$2:F$195,"INATIVO") | E7: =SE(B7>0,C7/B7,0)
A8: HOLDING | B8: =CONT.SE(Dados!A$2:A$195,"HOLDING") | C8: =CONT.SES(Dados!A$2:A$195,"HOLDING",Dados!F$2:F$195,"ATIVO") | D8: =CONT.SES(Dados!A$2:A$195,"HOLDING",Dados!F$2:F$195,"INATIVO") | E8: =SE(B8>0,C8/B8,0)
A9: MEDSERVICE | B9: =CONT.SE(Dados!A$2:A$195,"MEDSERVICE") | C9: =CONT.SES(Dados!A$2:A$195,"MEDSERVICE",Dados!F$2:F$195,"ATIVO") | D9: =CONT.SES(Dados!A$2:A$195,"MEDSERVICE",Dados!F$2:F$195,"INATIVO") | E9: =SE(B9>0,C9/B9,0)
A10: NOVAMED | B10: =CONT.SE(Dados!A$2:A$195,"NOVAMED") | C10: =CONT.SES(Dados!A$2:A$195,"NOVAMED",Dados!F$2:F$195,"ATIVO") | D10: =CONT.SES(Dados!A$2:A$195,"NOVAMED",Dados!F$2:F$195,"INATIVO") | E10: =SE(B10>0,C10/B10,0)
A11: SAUDE | B11: =CONT.SE(Dados!A$2:A$195,"SAUDE") | C11: =CONT.SES(Dados!A$2:A$195,"SAUDE",Dados!F$2:F$195,"ATIVO") | D11: =CONT.SES(Dados!A$2:A$195,"SAUDE",Dados!F$2:F$195,"INATIVO") | E11: =SE(B11>0,C11/B11,0)
A12: SAUDE OPERADORA | B12: =CONT.SE(Dados!A$2:A$195,"SAUDE OPERADORA") | C12: =CONT.SES(Dados!A$2:A$195,"SAUDE OPERADORA",Dados!F$2:F$195,"ATIVO") | D12: =CONT.SES(Dados!A$2:A$195,"SAUDE OPERADORA",Dados!F$2:F$195,"INATIVO") | E12: =SE(B12>0,C12/B12,0)
A13: TOTAL | B13: =SOMA(B3:B12) | C13: =SOMA(C3:C12) | D13: =SOMA(D3:D12) | E13: =SE(B13>0,C13/B13,0)

Sheet Benchmarking Mercer
A1: Benchmarking Mercer – Cobertura 2025 vs 2026
A2: Indicador | B2: Quantidade | C2: % Total
A3: Cargos com Mercer 2025 | B3: =CONT.SE(Dados!T$2:T$195,"<>"&"") | C3: =B3/CONT.VALORES(Dados!A$2:A$195)
A4: Cargos com Mercer 2026 | B4: =CONT.SE(Dados!U$2:U$195,"<>"&"") | C4: =B4/CONT.VALORES(Dados!A$2:A$195)
A5: Cargos SEM Mercer 2026 | B5: =CONT.SE(Dados!U$2:U$195,"") | C5: =B5/CONT.VALORES(Dados!A$2:A$195)
A6: % Cobertura Mercer 2026 | C6: =B4/CONT.VALORES(Dados!A$2:A$195)
A9: Cargos SEM Cod. Mercer 2026 — total: 16
A10: Cargo | B10: Empresa | C10: Grade | D10: Família GBS | E10: Situação
A11: ASSISTENTE ADMINISTRATIVO I | B11: HOLDING | C11: 4 | D11: Administração & Serviços | E11: ATIVO
A12: ANALISTA PROJETOS OBRAS | B12: BSP | C12: 5 | D12: Arquitetura & Engenharia | E12: ATIVO
A13: ARQUITETO I | B13: BSP | C13: 7 | D13: Arquitetura & Engenharia | E13: ATIVO
A14: ARQUITETO I | B14: HOLDING | C14: 7 | D14: Arquitetura & Engenharia | E14: ATIVO
A15: ENGENHEIRO I | B15: BSP | C15: 7 | D15: Arquitetura & Engenharia | E15: ATIVO
A16: ENGENHEIRO I | B16: HOLDING | C16: 7 | D16: Arquitetura & Engenharia | E16: ATIVO
A17: ARQUITETO II | B17: BSP | C17: 9 | D17: Arquitetura & Engenharia | E17: ATIVO
A18: ARQUITETO II | B18: HOLDING | C18: 9 | D18: Arquitetura & Engenharia | E18: ATIVO
A19: ENGENHEIRO II | B19: BSP | C19: 9 | D19: Arquitetura & Engenharia | E19: ATIVO
A20: ENGENHEIRO II | B20: HOLDING | C20: 9 | D20: Arquitetura & Engenharia | E20: ATIVO
A21: ARQUITETO III | B21: BSP | C21: 10 | D21: Arquitetura & Engenharia | E21: ATIVO
A22: ARQUITETO COORDENADOR | B22: HOLDING | C22: 10 | D22: Arquitetura & Engenharia | E22: ATIVO
... A26: GERENTE ENGENHARIA | B26: BSP | C26: 11 | D26: Arquitetura & Engenharia | E26: ATIVO

Sheet Pirâmide Hierárquica
A1: Pirâmide Hierárquica – Cargos Ativos
A2: Grupo Hierárquico | B2: Cargos Ativos | C2: Cargos Inativos | D2: Total
A3: GA | B3: =CONT.SES(Dados!J$2:J$195,"GA",Dados!F$2:F$195,"ATIVO") | C3: =CONT.SES(Dados!J$2:J$195,"GA",Dados!F$2:F$195,"INATIVO") | D3: =B3+C3
A4: GS | B4: =CONT.SES(Dados!J$2:J$195,"GS",Dados!F$2:F$195,"ATIVO") | C4: =CONT.SES(Dados!J$2:J$195,"GS",Dados!F$2:F$195,"INATIVO") | D4: =B4+C4
A5: Coordenador | B5: =CONT.SES(Dados!J$2:J$195,"Coordenador",Dados!F$2:F$195,"ATIVO") | C5: =CONT.SES(Dados!J$2:J$195,"Coordenador",Dados!F$2:F$195,"INATIVO") | D5: =B5+C5
A6: Supervisor | B6: =CONT.SES(Dados!J$2:J$195,"Supervisor",Dados!F$2:F$195,"ATIVO") | C6: =CONT.SES(Dados!J$2:J$195,"Supervisor",Dados!F$2:F$195,"INATIVO") | D6: =B6+C6
A7: Especialista | B7: =CONT.SES(Dados!J$2:J$195,"Especialista",Dados!F$2:F$195,"ATIVO") | C7: =CONT.SES(Dados!J$2:J$195,"Especialista",Dados!F$2:F$195,"INATIVO") | D7: =B7+C7
A8: Analista | B8: =CONT.SES(Dados!J$2:J$195,"Analista",Dados!F$2:F$195,"ATIVO") | C8: =CONT.SES(Dados!J$2:J$195,"Analista",Dados!F$2:F$195,"INATIVO") | D8: =B8+C8
A9: Assistente | B9: =CONT.SES(Dados!J$2:J$195,"Assistente",Dados!F$2:F$195,"ATIVO") | C9: =CONT.SES(Dados!J$2:J$195,"Assistente",Dados!F$2:F$195,"INATIVO") | D9: =B9+C9
A10: Auxiliar | B10: =CONT.SES(Dados!J$2:J$195,"Auxiliar",Dados!F$2:F$195,"ATIVO") | C10: =CONT.SES(Dados!J$2:J$195,"Auxiliar",Dados!F$2:F$195,"INATIVO") | D10: =B10+C10
A11: TOTAL | B11: =SOMA(B3:B10) | C11: =SOMA(C3:C10) | D11: =SOMA(D3:D10)
